fspin/RateControl.py
fspin/__init__.py
fspin/__main__.py
fspin/decorators.py
fspin/fspin_cheatsheet.md
fspin/loop_context.py
fspin/rate_control.py
fspin/reporting.py
fspin/spin_context.py
fspin/unified.py
fspin-0.3.9.dist-info/licenses/LICENSE.txt
fspin-0.3.9.dist-info/METADATA
fspin-0.3.9.dist-info/WHEEL
fspin-0.3.9.dist-info/top_level.txt
fspin-0.3.9.dist-info/RECORD
